grobid_client/__init__.py
grobid_client/client.py
grobid_client/grobid_client.py
PVPdarshan-3.3.3.dist-info/LICENSE
PVPdarshan-3.3.3.dist-info/METADATA
PVPdarshan-3.3.3.dist-info/WHEEL
PVPdarshan-3.3.3.dist-info/entry_points.txt
PVPdarshan-3.3.3.dist-info/top_level.txt
PVPdarshan-3.3.3.dist-info/RECORD
