Metadata-Version: 2.1
Name: PVPdarshan
Version: 3.3.3
Summary: grobid_client_python
Home-page: UNKNOWN
Author: kermitt2
License: LICENSE
Platform: UNKNOWN
License-File: LICENSE
Requires-Dist: requests
